{
  "generated_at": "2026-03-19T01:55:38.212Z",
  "alerts": [
    {
      "alert_id": "h-kannammoola-uppidamoodu:2026-03-19T01:55:38.212Z",
      "area_id": "h-kannammoola-uppidamoodu",
      "area_type": "hotspot",
      "district_id": "thiruvananthapuram",
      "name": "Kannammoola - Uppidamoodu canals",
      "score": 35.5,
      "valid_from": "2026-03-19T01:55:38.212Z",
      "valid_to": "2026-03-19T07:55:38.212Z",
      "level": "Watch",
      "confidence": 0.4,
      "review_state": "auto_published",
      "drivers": [
        "Observed 24h rain 6.9 mm and 1h rain 0.2 mm",
        "Peak recent 30 min rain 0.2 mm",
        "Rainfall aggregation district_polygon_mean",
        "RainViewer nowcast heavy (36 dBZ)",
        "Terrain susceptibility 52% from NASADEM + local baseline",
        "Reservoir caution active",
        "Dam downstream caution active",
        "Hotspot radar echo heavy (36 dBZ)",
        "Hotspot susceptibility 72%",
        "Hotspot category urban flood pocket",
        "Hotspot analysis radius 4 km"
      ],
      "source_refs": [
        {
          "source_id": "imd-cap-rss",
          "detail": "0 CAP items",
          "freshness_minutes": 2108,
          "status": "stale"
        },
        {
          "source_id": "imd-flash-flood-bulletin",
          "detail": "No Kerala bulletin trigger",
          "freshness_minutes": null,
          "status": "offline"
        },
        {
          "source_id": "indiawris-rainfall",
          "detail": "No India-WRIS rainfall signal mapped for district",
          "freshness_minutes": null,
          "status": "offline"
        },
        {
          "source_id": "rainviewer-radar",
          "detail": "RainViewer heavy cell near hotspot",
          "freshness_minutes": 0,
          "status": "ok"
        },
        {
          "source_id": "indiawris-river-level",
          "detail": "No India-WRIS river-level context for district",
          "freshness_minutes": null,
          "status": "offline"
        },
        {
          "source_id": "cwc-ffs",
          "detail": "No river-stage warning for district",
          "freshness_minutes": null,
          "status": "offline"
        }
      ],
      "message_en": "Kannammoola - Uppidamoodu canals: Watch. Observed 24h rain 6.9 mm and 1h rain 0.2 mm",
      "recommended_actions": [
        "Continue district monitoring.",
        "Watch official IMD and district warnings for changes."
      ]
    }
  ]
}
