{
  "generated_at": "2026-03-25T21:49:40.987Z",
  "source_count": 10,
  "online_sources": 2,
  "severe_pending_count": 0,
  "total_source_duration_ms": 4142484,
  "slowest_sources": [
    {
      "source_id": "cwc-ffs",
      "duration_ms": 1349947,
      "status": "offline",
      "fetch_status": "ok",
      "parser_status": "ok"
    },
    {
      "source_id": "imd-cap-rss",
      "duration_ms": 1327687,
      "status": "offline",
      "fetch_status": "failed",
      "parser_status": "skipped"
    },
    {
      "source_id": "rainviewer-radar",
      "duration_ms": 1310564,
      "status": "offline",
      "fetch_status": "failed",
      "parser_status": "skipped"
    },
    {
      "source_id": "nasa-imerg-nrt",
      "duration_ms": 87063,
      "status": "ok",
      "fetch_status": "ok",
      "parser_status": "ok"
    },
    {
      "source_id": "operator-observations",
      "duration_ms": 39389,
      "status": "degraded",
      "fetch_status": "ok",
      "parser_status": "ok"
    }
  ]
}
